journey_map/__init__.py
journey_map/admin/__init__.py
journey_map/admin/inlines.py
journey_map/admin/journey_action.py
journey_map/admin/journey_stage.py
journey_map/admin/opportunity.py
journey_map/admin/pain_point.py
journey_map/admin/user_feedback.py
journey_map/admin/user_journey.py
journey_map/api/__init__.py
journey_map/api/filters/__init__.py
journey_map/api/filters/journey_action.py
journey_map/api/filters/journey_stage.py
journey_map/api/filters/opportunity.py
journey_map/api/filters/pain_point.py
journey_map/api/filters/user_feedback.py
journey_map/api/filters/user_journey.py
journey_map/api/paginations/__init__.py
journey_map/api/paginations/limit_offset_pagination.py
journey_map/api/routers/__init__.py
journey_map/api/routers/main.py
journey_map/api/serializers/__init__.py
journey_map/api/serializers/helper/get_serializer_cls.py
journey_map/api/serializers/journey_action.py
journey_map/api/serializers/journey_stage.py
journey_map/api/serializers/opportunity.py
journey_map/api/serializers/pain_point.py
journey_map/api/serializers/user_feedback.py
journey_map/api/serializers/user_journey.py
journey_map/api/throttlings/__init__.py
journey_map/api/throttlings/role_base_throttle.py
journey_map/api/views/__init__.py
journey_map/api/views/base.py
journey_map/api/views/journey_action.py
journey_map/api/views/journey_stage.py
journey_map/api/views/opportunity.py
journey_map/api/views/pain_point.py
journey_map/api/views/user_feedback.py
journey_map/api/views/user_journey.py
journey_map/apps.py
journey_map/constants/__init__.py
journey_map/constants/default_settings.py
journey_map/constants/types.py
journey_map/migrations/0001_initial.py
journey_map/migrations/__init__.py
journey_map/mixins/__init__.py
journey_map/mixins/admin/__init__.py
journey_map/mixins/admin/base.py
journey_map/mixins/admin/inlines.py
journey_map/mixins/admin/permission.py
journey_map/mixins/api/__init__.py
journey_map/mixins/api/config_api_attrs.py
dj_userjourney_map-1.0.0.dist-info/AUTHORS.md
dj_userjourney_map-1.0.0.dist-info/LICENSE
dj_userjourney_map-1.0.0.dist-info/METADATA
dj_userjourney_map-1.0.0.dist-info/WHEEL
dj_userjourney_map-1.0.0.dist-info/RECORD
